update_playlist/__init__.py
update_playlist/config.py
update_playlist/file_manager.py
update_playlist/main.py
update_playlist/playlist.py
update_playlist/spotify.py
update_playlist-0.2.1.dist-info/licenses/LICENSE
update_playlist-0.2.1.dist-info/METADATA
update_playlist-0.2.1.dist-info/WHEEL
update_playlist-0.2.1.dist-info/entry_points.txt
update_playlist-0.2.1.dist-info/top_level.txt
update_playlist-0.2.1.dist-info/RECORD
