Metadata-Version: 2.4
Name: update-playlist
Version: 0.2.1
Summary: A modular playlist manager to download and manage Spotify playlists.
Author-email: Antonio Labate <antoniolabate19@gmail.com>
Project-URL: Homepage, https://github.com/totolab/update_playlist
Project-URL: Bug Tracker, https://github.com/totolab/update_playlist/issues
Classifier: Programming Language :: Python :: 3
Classifier: License :: OSI Approved :: MIT License
Classifier: Operating System :: OS Independent
Requires-Python: >=3.8
License-File: LICENSE
Requires-Dist: spotdl
Requires-Dist: yt-dlp
Requires-Dist: requests
Dynamic: license-file
